tempusloader/__init__.py
tempusloader/load_tempus.py
tempusloader/provider/__init__.py
tempusloader/provider/config.py
tempusloader/provider/dbtools.py
tempusloader/provider/importer.py
tempusloader/provider/navteq.py
tempusloader/provider/osm.py
tempusloader/provider/poi.py
tempusloader/provider/pt.py
tempusloader/provider/reset.py
tempusloader/provider/road.py
tempusloader/provider/route120.py
tempusloader/provider/route500.py
tempusloader/provider/tomtom.py
tempusloader/provider/tools.py
tempusloader/provider/sql/create_gtfs_import_tables.sql
tempusloader/provider/sql/create_road_indexes.sql
tempusloader/provider/sql/dem_elevation.sql
tempusloader/provider/sql/drop_road_indexes.sql
tempusloader/provider/sql/gtfs.sql
tempusloader/provider/sql/gtfs_shapes.sql
tempusloader/provider/sql/multinet.sql
tempusloader/provider/sql/multinet1409.sql
tempusloader/provider/sql/navteq.sql
tempusloader/provider/sql/poi.sql
tempusloader/provider/sql/pt_cleaning.sql
tempusloader/provider/sql/reset_import_schema.sql
tempusloader/provider/sql/road.sql
tempusloader/provider/sql/road_cleaning.sql
tempusloader/provider/sql/route120.sql
tempusloader/provider/sql/route500.sql
tempusloader/provider/sql/tempus.sql
tempusloader-1.0.0.dist-info/DESCRIPTION.rst
tempusloader-1.0.0.dist-info/METADATA
tempusloader-1.0.0.dist-info/RECORD
tempusloader-1.0.0.dist-info/WHEEL
tempusloader-1.0.0.dist-info/entry_points.txt
tempusloader-1.0.0.dist-info/metadata.json
tempusloader-1.0.0.dist-info/top_level.txt
